vickitrix/__init__.py
vickitrix/__main__.py
vickitrix/rules/sentiment.py
vickitrix/rules/vicki.py
vickitrix-0.1.5.dist-info/DESCRIPTION.rst
vickitrix-0.1.5.dist-info/METADATA
vickitrix-0.1.5.dist-info/RECORD
vickitrix-0.1.5.dist-info/WHEEL
vickitrix-0.1.5.dist-info/entry_points.txt
vickitrix-0.1.5.dist-info/metadata.json
vickitrix-0.1.5.dist-info/top_level.txt
vickitrix-0.1.5.dist-info/zip-safe
